.gitignore
LICENSE
MANIFEST.in
Makefile
README.rst
setup.py
src/__init__.py
src/parser.py
src/specs/parsing_invalid_stories.py
src/specs/parsing_valid_stories.py
src/specs/regex_with_i18n.py
src/specs/run_all_specs.py
story_parser.egg-info/PKG-INFO
story_parser.egg-info/SOURCES.txt
story_parser.egg-info/dependency_links.txt
story_parser.egg-info/entry_points.txt
story_parser.egg-info/not-zip-safe
story_parser.egg-info/top_level.txt