Metadata-Version: 1.0
Name: story_parser
Version: 0.1.2
Summary: A Given/When/Then BDD stories parser
Home-page: http://github.com/hugobr/story_parser
Author: Hugo Lopes Tavares
Author-email: hltbra@gmail.com
License: MIT
Keywords: bdd story parser
Platform: UNKNOWN
